rocksdb/__init__.py
rocksdb/_rocksdb.cpython-36m-darwin.so
rocksdb/errors.py
rocksdb/interfaces.py
rocksdb/merge_operators.py
rocksdb/tests/__init__.py
rocksdb/tests/test_db.py
rocksdb/tests/test_memtable.py
rocksdb/tests/test_options.py
python_rocksdb_static-0.7.9.dist-info/LICENSE.md
python_rocksdb_static-0.7.9.dist-info/METADATA
python_rocksdb_static-0.7.9.dist-info/WHEEL
python_rocksdb_static-0.7.9.dist-info/top_level.txt
python_rocksdb_static-0.7.9.dist-info/RECORD
